{
  "name": "IPAM Autopilot",
  "image": "golang:1.26-bookworm",

  "features": {
    "ghcr.io/devcontainers/features/docker-in-docker:2": {},
    "ghcr.io/devcontainers/features/common-utils:2": {
      "installZsh": true,
      "configureZshAsDefaultShell": true
    }
  },

  "onCreateCommand": "bash .devcontainer/install-tools.sh",

  "customizations": {
    "vscode": {
      "extensions": [
        "golang.go",
        "ms-azuretools.vscode-docker",
        "HashiCorp.HCL",
        "hashicorp.terraform",
        "exiasr.hadolint"
      ],
      "settings": {
        "go.toolsManagement.checkForUpdates": "local",
        "go.useLanguageServer": true,
        "go.lintTool": "golangci-lint",
        "go.lintFlags": ["--fast"],
        "files.associations": {
          "*.hcl": "hcl",
          "*.tftest.hcl": "hcl",
          "*.tf": "hcl",
          "*.tfvars": "hcl",
          "*.tfrc": "hcl"
        }
      }
    }
  },

  "remoteUser": "root",
  "workspaceFolder": "/workspace",
  "workspaceMount": "source=${localWorkspaceFolder},target=/workspace,type=bind"
}
